nostr_agents/__init__.py
nostr_agents/nostr_agent_server.py
nostr_agents/nostr_client.py
nostr_agents/nostr_mcp_client.py
nostr_agents/nostr_mcp_server.py
nostr_agents/nwc.py
nostr_agents/nwc_client.py
nostr_agents-0.0.1.dist-info/licenses/LICENSE
nostr_agents-0.0.1.dist-info/METADATA
nostr_agents-0.0.1.dist-info/WHEEL
nostr_agents-0.0.1.dist-info/top_level.txt
nostr_agents-0.0.1.dist-info/RECORD
